mathematics/__init__.py
mathematics/function.py
mathematics/grow_lists.py
mathematics/hold_list.py
mathematics/lists.py
mathematics-0a1.dev2022411.dist-info/LICENSE
mathematics-0a1.dev2022411.dist-info/METADATA
mathematics-0a1.dev2022411.dist-info/WHEEL
mathematics-0a1.dev2022411.dist-info/top_level.txt
mathematics-0a1.dev2022411.dist-info/RECORD
