Metadata-Version: 2.1
Name: mathematics
Version: 0a1.dev2022411
Summary: A package with mathematical functions
Home-page: https://github.com/arihant2math/mathemathics
Author: Ashwin Naren
Author-email: arihant2math@gmail.com
License: UNKNOWN
Platform: UNKNOWN
Classifier: Development Status :: 3 - Alpha
Classifier: Programming Language :: Python :: 3
Classifier: License :: OSI Approved :: MIT License
Classifier: Operating System :: OS Independent
Classifier: Natural Language :: English
Classifier: Intended Audience :: Developers
Requires: numpy
Requires: matplotlib
Requires-Python: >=3.8
License-File: LICENSE
